llm_registry/__init__.py
llm_registry/cli.py
llm_registry/exceptions.py
llm_registry/models.py
llm_registry/py.typed
llm_registry/registry.py
llm_registry/repository.py
llm_registry/utils.py
llm_registry/data/models.json
llm_registry-0.4.8.dist-info/METADATA
llm_registry-0.4.8.dist-info/WHEEL
llm_registry-0.4.8.dist-info/entry_points.txt
llm_registry-0.4.8.dist-info/licenses/LICENSE
llm_registry-0.4.8.dist-info/RECORD
