Metadata-Version: 2.4
Name: llm-registry
Version: 0.4.8
Summary: A centralized registry for discovering and managing LLM model capabilities. Track model features, costs, and limitations across providers like OpenAI and Anthropic. Supports both verified model definitions and user-managed entries with local storage.
Project-URL: Homepage, https://github.com/yamanahlawat/llm-registry
Project-URL: Issues, https://github.com/yamanahlawat/llm-registry/issues
Author-email: Yaman Ahlawat <yaman@outlook.com>
License-File: LICENSE
Requires-Python: >=3.11
Requires-Dist: httpx>=0.28.1
Requires-Dist: pydantic>=2.12.5
Requires-Dist: rich>=14.2.0
Requires-Dist: typer>=0.20.1
